{
  "11234567890": [
    {
      "message": "no",
      "timestamp": "2025-07-25T16:34:48.789Z"
    },
    {
      "message": "i'll let you know",
      "timestamp": "2025-07-25T16:36:06.873Z"
    },
    {
      "message": "yes",
      "timestamp": "2025-07-25T17:48:45.479Z"
    },
    {
      "message": "yes",
      "timestamp": "2025-07-25T17:49:46.631Z"
    },
    {
      "message": "yes",
      "timestamp": "2025-07-25T17:50:32.948Z"
    },
    {
      "message": "yes",
      "timestamp": "2025-07-25T17:50:46.752Z"
    },
    {
      "message": "yes",
      "timestamp": "2025-07-25T17:55:48.209Z"
    },
    {
      "message": "yes",
      "timestamp": "2025-07-25T17:59:36.545Z"
    },
    {
      "message": "yes",
      "timestamp": "2025-07-25T18:03:18.944Z"
    },
    {
      "message": "yes",
      "timestamp": "2025-07-25T18:21:14.602Z"
    },
    {
      "message": "yes",
      "timestamp": "2025-07-25T18:24:48.958Z"
    },
    {
      "message": "yes",
      "timestamp": "2025-07-25T18:36:57.936Z"
    }
  ]
}
